mgrsconv/__init__.py
mgrsconv/mgrsconv.py
mgrsconv-0.0.11.dist-info/licenses/LICENSE
mgrsconv-0.0.11.dist-info/METADATA
mgrsconv-0.0.11.dist-info/WHEEL
mgrsconv-0.0.11.dist-info/top_level.txt
mgrsconv-0.0.11.dist-info/RECORD
