Metadata-Version: 2.4
Name: mgrsconv
Version: 0.0.11
Summary: Convert between Decimal Degrees and MGRS coordinates
Home-page: https://github.com/nousernamesavailabel/MGRSConv
Author: Jared Polack
Author-email: jaredpolack@gmail.com
Classifier: Programming Language :: Python :: 3
Classifier: License :: OSI Approved :: MIT License
Classifier: Operating System :: OS Independent
Requires-Python: >=3.6
License-File: LICENSE
Dynamic: author
Dynamic: author-email
Dynamic: classifier
Dynamic: description
Dynamic: description-content-type
Dynamic: home-page
Dynamic: license-file
Dynamic: requires-python
Dynamic: summary
